MANIFEST.in
README.txt
setup.cfg
setup.py
docs/HISTORY.txt
docs/INSTALL.txt
docs/LICENSE.GPL
docs/LICENSE.txt
quintagroup/__init__.py
quintagroup.portletmanager.footer.egg-info/PKG-INFO
quintagroup.portletmanager.footer.egg-info/SOURCES.txt
quintagroup.portletmanager.footer.egg-info/dependency_links.txt
quintagroup.portletmanager.footer.egg-info/entry_points.txt
quintagroup.portletmanager.footer.egg-info/namespace_packages.txt
quintagroup.portletmanager.footer.egg-info/not-zip-safe
quintagroup.portletmanager.footer.egg-info/requires.txt
quintagroup.portletmanager.footer.egg-info/top_level.txt
quintagroup/portletmanager/__init__.py
quintagroup/portletmanager/footer/__init__.py
quintagroup/portletmanager/footer/configure.zcml
quintagroup/portletmanager/footer/interfaces.py
quintagroup/portletmanager/footer/manager.py
quintagroup/portletmanager/footer/profiles/default/metadata.xml
quintagroup/portletmanager/footer/profiles/default/portlets.xml
quintagroup/portletmanager/footer/templates/error_message.pt
quintagroup/portletmanager/footer/templates/footer_portlets.pt
quintagroup/portletmanager/footer/templates/manage_footer.pt
quintagroup/portletmanager/footer/templates/portlets.pt