Metadata-Version: 1.0
Name: quintagroup.portletmanager.footer
Version: 0.1
Summary: Portlet manager that is rendered in page footer
Home-page: http://svn.quintagroup.com/products/quintagroup.portletmanager.footer/trunk
Author: Bohdan Koval
Author-email: koval@quintagroup.com
License: GPL
Keywords: plone portletmanager footer
Platform: UNKNOWN
Classifier: Programming Language :: Python
Classifier: Topic :: Software Development :: Libraries :: Python Modules
